{"watchedBy":[{"customer-id":"14556191","movie-id":"1037289","rating":2,"date":"2003-03-27"},{"customer-id":"14424031","movie-id":"1037289","rating":4,"date":"2002-01-13"},{"customer-id":"16732614","movie-id":"1037289","rating":4,"date":"2002-01-12"},{"customer-id":"14611995","movie-id":"1037289","rating":4,"date":"2005-08-28"},{"customer-id":"15998136","movie-id":"1037289","rating":2,"date":"2005-05-27"},{"customer-id":"14664895","movie-id":"1037289","rating":5,"date":"2005-07-04"},{"customer-id":"16995355","movie-id":"1037289","rating":4,"date":"2005-12-06"},{"customer-id":"16533475","movie-id":"1037289","rating":5,"date":"2003-01-22"},{"customer-id":"16071068","movie-id":"1037289","rating":3,"date":"2005-05-07"},{"customer-id":"16325794","movie-id":"1037289","rating":3,"date":"2002-05-06"},{"customer-id":"14395246","movie-id":"1037289","rating":4,"date":"2005-08-30"},{"customer-id":"16059694","movie-id":"1037289","rating":4,"date":"2002-02-11"},{"customer-id":"14796305","movie-id":"1037289","rating":3,"date":"2003-05-07"},{"customer-id":"14626361","movie-id":"1037289","rating":4,"date":"2005-08-29"},{"customer-id":"14651783","movie-id":"1037289","rating":3,"date":"2005-03-29"},{"customer-id":"16592684","movie-id":"1037289","rating":1,"date":"2005-04-06"},{"customer-id":"14510183","movie-id":"1037289","rating":5,"date":"2003-04-21"},{"customer-id":"15157778","movie-id":"1037289","rating":3,"date":"2005-06-21"},{"customer-id":"16251010","movie-id":"1037289","rating":1,"date":"2001-07-11"},{"customer-id":"15529385","movie-id":"1037289","rating":5,"date":"2005-07-23"},{"customer-id":"16942409","movie-id":"1037289","rating":4,"date":"2002-04-26"},{"customer-id":"15600809","movie-id":"1037289","rating":2,"date":"2003-07-19"},{"customer-id":"15708531","movie-id":"1037289","rating":4,"date":"2005-10-18"},{"customer-id":"15930247","movie-id":"1037289","rating":2,"date":"2002-03-07"},{"customer-id":"15277143","movie-id":"1037289","rating":4,"date":"2002-12-04"},{"customer-id":"16440893","movie-id":"1037289","rating":3,"date":"2001-09-07"},{"customer-id":"16909696","movie-id":"1037289","rating":3,"date":"2002-08-18"},{"customer-id":"15268717","movie-id":"1037289","rating":3,"date":"2003-02-11"},{"customer-id":"14873191","movie-id":"1037289","rating":1,"date":"2002-12-10"},{"customer-id":"14413944","movie-id":"1037289","rating":1,"date":"2003-06-15"},{"customer-id":"16131985","movie-id":"1037289","rating":4,"date":"2005-07-28"},{"customer-id":"14621780","movie-id":"1037289","rating":3,"date":"2005-06-07"},{"customer-id":"16147571","movie-id":"1037289","rating":1,"date":"2003-01-10"},{"customer-id":"15642690","movie-id":"1037289","rating":3,"date":"2003-01-17"},{"customer-id":"15657673","movie-id":"1037289","rating":5,"date":"2005-06-12"},{"customer-id":"16868348","movie-id":"1037289","rating":3,"date":"2003-08-21"},{"customer-id":"15574679","movie-id":"1037289","rating":2,"date":"2003-04-03"},{"customer-id":"15089258","movie-id":"1037289","rating":3,"date":"2003-06-22"},{"customer-id":"16595625","movie-id":"1037289","rating":3,"date":"2005-06-21"},{"customer-id":"15636909","movie-id":"1037289","rating":1,"date":"2002-12-31"},{"customer-id":"16168795","movie-id":"1037289","rating":3,"date":"2005-05-25"},{"customer-id":"14759231","movie-id":"1037289","rating":4,"date":"2002-01-06"},{"customer-id":"15064709","movie-id":"1037289","rating":4,"date":"2005-05-25"},{"customer-id":"15922099","movie-id":"1037289","rating":4,"date":"2005-06-12"},{"customer-id":"16100105","movie-id":"1037289","rating":4,"date":"2002-01-01"},{"customer-id":"16988385","movie-id":"1037289","rating":2,"date":"2002-11-28"},{"customer-id":"15014418","movie-id":"1037289","rating":3,"date":"2005-04-04"},{"customer-id":"16006788","movie-id":"1037289","rating":3,"date":"2005-06-26"},{"customer-id":"16895828","movie-id":"1037289","rating":3,"date":"2002-03-30"},{"customer-id":"14397420","movie-id":"1037289","rating":1,"date":"2003-01-20"},{"customer-id":"16078901","movie-id":"1037289","rating":3,"date":"2002-06-07"},{"customer-id":"16516335","movie-id":"1037289","rating":3,"date":"2002-09-21"},{"customer-id":"14583624","movie-id":"1037289","rating":4,"date":"2005-07-25"},{"customer-id":"14589607","movie-id":"1037289","rating":4,"date":"2005-08-26"},{"customer-id":"15983543","movie-id":"1037289","rating":5,"date":"2005-10-03"},{"customer-id":"15709453","movie-id":"1037289","rating":2,"date":"2003-08-23"},{"customer-id":"15719257","movie-id":"1037289","rating":2,"date":"2005-06-10"},{"customer-id":"14684531","movie-id":"1037289","rating":4,"date":"2005-07-10"},{"customer-id":"15620214","movie-id":"1037289","rating":1,"date":"2002-03-25"},{"customer-id":"16898673","movie-id":"1037289","rating":4,"date":"2002-06-30"},{"customer-id":"16519553","movie-id":"1037289","rating":5,"date":"2005-11-03"},{"customer-id":"15930629","movie-id":"1037289","rating":1,"date":"2005-11-08"},{"customer-id":"16140576","movie-id":"1037289","rating":3,"date":"2002-08-13"},{"customer-id":"15480775","movie-id":"1037289","rating":2,"date":"2002-07-16"},{"customer-id":"15923297","movie-id":"1037289","rating":5,"date":"2005-08-30"},{"customer-id":"15662704","movie-id":"1037289","rating":4,"date":"2005-04-06"},{"customer-id":"16669498","movie-id":"1037289","rating":4,"date":"2002-10-19"},{"customer-id":"14852046","movie-id":"1037289","rating":2,"date":"2001-12-12"},{"customer-id":"16168726","movie-id":"1037289","rating":3,"date":"2003-03-10"},{"customer-id":"15207661","movie-id":"1037289","rating":3,"date":"2002-09-15"},{"customer-id":"15465033","movie-id":"1037289","rating":3,"date":"2005-09-02"},{"customer-id":"14711566","movie-id":"1037289","rating":4,"date":"2003-01-19"},{"customer-id":"16511206","movie-id":"1037289","rating":3,"date":"2002-11-06"},{"customer-id":"16787328","movie-id":"1037289","rating":1,"date":"2003-01-14"},{"customer-id":"15123156","movie-id":"1037289","rating":5,"date":"2005-06-28"},{"customer-id":"15339092","movie-id":"1037289","rating":5,"date":"2002-04-12"},{"customer-id":"16327974","movie-id":"1037289","rating":4,"date":"2005-07-05"},{"customer-id":"15832533","movie-id":"1037289","rating":5,"date":"2003-07-07"},{"customer-id":"15877639","movie-id":"1037289","rating":2,"date":"2001-05-13"},{"customer-id":"15130143","movie-id":"1037289","rating":4,"date":"2002-11-17"},{"customer-id":"15830477","movie-id":"1037289","rating":2,"date":"2003-03-23"},{"customer-id":"14683585","movie-id":"1037289","rating":2,"date":"2002-07-09"},{"customer-id":"16145078","movie-id":"1037289","rating":2,"date":"2003-03-30"},{"customer-id":"15489553","movie-id":"1037289","rating":5,"date":"2005-08-29"},{"customer-id":"14586575","movie-id":"1037289","rating":3,"date":"2005-06-06"},{"customer-id":"14894480","movie-id":"1037289","rating":3,"date":"2005-06-18"},{"customer-id":"16830573","movie-id":"1037289","rating":5,"date":"2002-08-27"},{"customer-id":"15989048","movie-id":"1037289","rating":3,"date":"2005-10-08"},{"customer-id":"16767749","movie-id":"1037289","rating":2,"date":"2002-01-08"},{"customer-id":"14840549","movie-id":"1037289","rating":3,"date":"2002-07-14"},{"customer-id":"16632508","movie-id":"1037289","rating":1,"date":"2003-02-28"},{"customer-id":"16510511","movie-id":"1037289","rating":4,"date":"2005-12-07"},{"customer-id":"14598344","movie-id":"1037289","rating":2,"date":"2005-06-05"},{"customer-id":"14873514","movie-id":"1037289","rating":2,"date":"2003-06-20"},{"customer-id":"15648522","movie-id":"1037289","rating":3,"date":"2005-07-04"},{"customer-id":"16503516","movie-id":"1037289","rating":1,"date":"2005-09-21"},{"customer-id":"15112620","movie-id":"1037289","rating":2,"date":"2001-06-28"},{"customer-id":"15190247","movie-id":"1037289","rating":3,"date":"2002-08-25"},{"customer-id":"14456840","movie-id":"1037289","rating":3,"date":"2002-03-14"},{"customer-id":"16979361","movie-id":"1037289","rating":3,"date":"2003-09-10"},{"customer-id":"16932087","movie-id":"1037289","rating":3,"date":"2001-06-02"},{"customer-id":"15111721","movie-id":"1037289","rating":4,"date":"2002-06-30"},{"customer-id":"14500494","movie-id":"1037289","rating":2,"date":"2005-07-31"},{"customer-id":"15457991","movie-id":"1037289","rating":2,"date":"2003-08-24"},{"customer-id":"15477572","movie-id":"1037289","rating":5,"date":"2005-09-11"},{"customer-id":"14571361","movie-id":"1037289","rating":5,"date":"2005-11-23"},{"customer-id":"15659181","movie-id":"1037289","rating":4,"date":"2001-06-16"},{"customer-id":"15054667","movie-id":"1037289","rating":3,"date":"2001-06-05"},{"customer-id":"16449467","movie-id":"1037289","rating":3,"date":"2002-04-09"},{"customer-id":"15503035","movie-id":"1037289","rating":3,"date":"2005-07-22"},{"customer-id":"16856400","movie-id":"1037289","rating":3,"date":"2005-09-01"},{"customer-id":"15944366","movie-id":"1037289","rating":5,"date":"2005-05-18"},{"customer-id":"15576821","movie-id":"1037289","rating":5,"date":"2005-11-06"},{"customer-id":"14732187","movie-id":"1037289","rating":1,"date":"2005-07-07"},{"customer-id":"16299576","movie-id":"1037289","rating":2,"date":"2002-08-17"},{"customer-id":"16125241","movie-id":"1037289","rating":3,"date":"2002-10-23"},{"customer-id":"15466948","movie-id":"1037289","rating":3,"date":"2005-08-11"},{"customer-id":"14858947","movie-id":"1037289","rating":3,"date":"2005-08-30"},{"customer-id":"16091693","movie-id":"1037289","rating":3,"date":"2003-09-23"},{"customer-id":"14553239","movie-id":"1037289","rating":3,"date":"2003-04-14"},{"customer-id":"16398553","movie-id":"1037289","rating":4,"date":"2002-10-01"},{"customer-id":"16080420","movie-id":"1037289","rating":3,"date":"2005-11-08"},{"customer-id":"15590241","movie-id":"1037289","rating":1,"date":"2002-07-14"},{"customer-id":"15135263","movie-id":"1037289","rating":2,"date":"2002-09-26"},{"customer-id":"16224355","movie-id":"1037289","rating":1,"date":"2002-05-03"},{"customer-id":"14442642","movie-id":"1037289","rating":5,"date":"2005-08-12"},{"customer-id":"15794610","movie-id":"1037289","rating":3,"date":"2002-06-11"},{"customer-id":"16889220","movie-id":"1037289","rating":5,"date":"2001-11-24"},{"customer-id":"16939930","movie-id":"1037289","rating":4,"date":"2005-07-28"},{"customer-id":"14601251","movie-id":"1037289","rating":2,"date":"2003-01-15"},{"customer-id":"16213681","movie-id":"1037289","rating":1,"date":"2002-10-15"},{"customer-id":"15622189","movie-id":"1037289","rating":3,"date":"2002-06-29"},{"customer-id":"16476900","movie-id":"1037289","rating":1,"date":"2003-03-24"},{"customer-id":"16808846","movie-id":"1037289","rating":2,"date":"2003-05-29"},{"customer-id":"15197902","movie-id":"1037289","rating":2,"date":"2002-11-03"},{"customer-id":"15206734","movie-id":"1037289","rating":2,"date":"2003-02-28"},{"customer-id":"15306036","movie-id":"1037289","rating":5,"date":"2005-03-21"},{"customer-id":"14601884","movie-id":"1037289","rating":2,"date":"2005-06-14"},{"customer-id":"16412999","movie-id":"1037289","rating":2,"date":"2005-12-01"},{"customer-id":"15906985","movie-id":"1037289","rating":4,"date":"2005-07-10"},{"customer-id":"16372415","movie-id":"1037289","rating":1,"date":"2002-06-19"},{"customer-id":"14455611","movie-id":"1037289","rating":3,"date":"2005-03-28"},{"customer-id":"16321709","movie-id":"1037289","rating":5,"date":"2005-08-01"},{"customer-id":"16601664","movie-id":"1037289","rating":3,"date":"2002-11-18"},{"customer-id":"14682609","movie-id":"1037289","rating":3,"date":"2002-10-21"},{"customer-id":"16138753","movie-id":"1037289","rating":5,"date":"2001-12-28"},{"customer-id":"15086225","movie-id":"1037289","rating":4,"date":"2005-12-05"},{"customer-id":"15680445","movie-id":"1037289","rating":5,"date":"2005-12-15"},{"customer-id":"15115793","movie-id":"1037289","rating":3,"date":"2003-06-03"},{"customer-id":"14358568","movie-id":"1037289","rating":2,"date":"2002-02-25"},{"customer-id":"15593152","movie-id":"1037289","rating":3,"date":"2005-08-11"},{"customer-id":"16344983","movie-id":"1037289","rating":4,"date":"2005-10-10"},{"customer-id":"15603647","movie-id":"1037289","rating":4,"date":"2005-07-29"},{"customer-id":"16240339","movie-id":"1037289","rating":3,"date":"2003-05-09"},{"customer-id":"15286766","movie-id":"1037289","rating":2,"date":"2002-05-31"},{"customer-id":"15349042","movie-id":"1037289","rating":5,"date":"2005-06-06"},{"customer-id":"16717655","movie-id":"1037289","rating":3,"date":"2005-11-20"},{"customer-id":"16495549","movie-id":"1037289","rating":3,"date":"2000-11-25"},{"customer-id":"15147277","movie-id":"1037289","rating":5,"date":"2002-11-20"},{"customer-id":"14596016","movie-id":"1037289","rating":5,"date":"2005-08-29"},{"customer-id":"16468699","movie-id":"1037289","rating":4,"date":"2002-06-12"},{"customer-id":"14689484","movie-id":"1037289","rating":3,"date":"2003-01-18"},{"customer-id":"14440221","movie-id":"1037289","rating":2,"date":"2002-10-21"},{"customer-id":"16561460","movie-id":"1037289","rating":2,"date":"2005-05-19"},{"customer-id":"15912230","movie-id":"1037289","rating":5,"date":"2005-07-21"},{"customer-id":"15988169","movie-id":"1037289","rating":4,"date":"2005-12-10"},{"customer-id":"14853152","movie-id":"1037289","rating":2,"date":"2001-01-11"},{"customer-id":"16431202","movie-id":"1037289","rating":3,"date":"2002-10-25"},{"customer-id":"15288541","movie-id":"1037289","rating":4,"date":"2005-04-05"},{"customer-id":"14507769","movie-id":"1037289","rating":3,"date":"2005-11-10"},{"customer-id":"14387132","movie-id":"1037289","rating":2,"date":"2005-08-08"},{"customer-id":"16849980","movie-id":"1037289","rating":5,"date":"2005-06-15"},{"customer-id":"14396116","movie-id":"1037289","rating":3,"date":"2005-06-19"},{"customer-id":"14858669","movie-id":"1037289","rating":3,"date":"2005-05-14"},{"customer-id":"15472619","movie-id":"1037289","rating":5,"date":"2005-06-06"},{"customer-id":"16011845","movie-id":"1037289","rating":4,"date":"2005-10-12"},{"customer-id":"15529444","movie-id":"1037289","rating":2,"date":"2002-09-02"},{"customer-id":"14961713","movie-id":"1037289","rating":2,"date":"2002-07-02"},{"customer-id":"16052811","movie-id":"1037289","rating":3,"date":"2005-03-25"},{"customer-id":"16682118","movie-id":"1037289","rating":5,"date":"2005-07-08"},{"customer-id":"14482585","movie-id":"1037289","rating":3,"date":"2005-09-02"},{"customer-id":"15443626","movie-id":"1037289","rating":1,"date":"2002-01-05"},{"customer-id":"16391619","movie-id":"1037289","rating":3,"date":"2001-04-30"},{"customer-id":"15552395","movie-id":"1037289","rating":4,"date":"2005-04-24"},{"customer-id":"15975132","movie-id":"1037289","rating":4,"date":"2002-05-21"},{"customer-id":"16045920","movie-id":"1037289","rating":2,"date":"2001-10-28"},{"customer-id":"15521043","movie-id":"1037289","rating":4,"date":"2001-08-18"},{"customer-id":"14803169","movie-id":"1037289","rating":3,"date":"2003-08-14"},{"customer-id":"16688337","movie-id":"1037289","rating":2,"date":"2005-08-24"},{"customer-id":"16370127","movie-id":"1037289","rating":3,"date":"2005-06-25"},{"customer-id":"15741847","movie-id":"1037289","rating":3,"date":"2005-10-07"},{"customer-id":"15981209","movie-id":"1037289","rating":3,"date":"2005-11-21"},{"customer-id":"15783726","movie-id":"1037289","rating":3,"date":"2005-05-02"},{"customer-id":"16890470","movie-id":"1037289","rating":3,"date":"2005-06-22"},{"customer-id":"16631530","movie-id":"1037289","rating":3,"date":"2002-08-16"},{"customer-id":"16500691","movie-id":"1037289","rating":4,"date":"2003-07-04"},{"customer-id":"15791297","movie-id":"1037289","rating":4,"date":"2005-11-02"},{"customer-id":"14653439","movie-id":"1037289","rating":5,"date":"2005-11-06"},{"customer-id":"15464987","movie-id":"1037289","rating":3,"date":"2005-07-27"},{"customer-id":"16591025","movie-id":"1037289","rating":5,"date":"2005-12-12"},{"customer-id":"16199264","movie-id":"1037289","rating":3,"date":"2002-07-02"},{"customer-id":"14729663","movie-id":"1037289","rating":4,"date":"2005-06-17"},{"customer-id":"15497250","movie-id":"1037289","rating":3,"date":"2002-11-16"},{"customer-id":"16428384","movie-id":"1037289","rating":3,"date":"2002-08-16"},{"customer-id":"15646346","movie-id":"1037289","rating":2,"date":"2002-04-29"},{"customer-id":"16482895","movie-id":"1037289","rating":2,"date":"2003-01-10"},{"customer-id":"16099398","movie-id":"1037289","rating":4,"date":"2005-10-30"},{"customer-id":"16428657","movie-id":"1037289","rating":2,"date":"2003-03-03"},{"customer-id":"14779680","movie-id":"1037289","rating":2,"date":"2003-05-02"},{"customer-id":"16353846","movie-id":"1037289","rating":3,"date":"2003-04-06"},{"customer-id":"14941061","movie-id":"1037289","rating":2,"date":"2000-02-19"},{"customer-id":"16574450","movie-id":"1037289","rating":3,"date":"2003-06-06"},{"customer-id":"16988595","movie-id":"1037289","rating":2,"date":"2001-11-15"},{"customer-id":"16066361","movie-id":"1037289","rating":3,"date":"2002-03-15"},{"customer-id":"14419429","movie-id":"1037289","rating":2,"date":"2000-09-02"},{"customer-id":"15997549","movie-id":"1037289","rating":5,"date":"2003-03-03"},{"customer-id":"14790111","movie-id":"1037289","rating":2,"date":"2003-07-10"},{"customer-id":"15271103","movie-id":"1037289","rating":3,"date":"2005-06-20"},{"customer-id":"15350778","movie-id":"1037289","rating":2,"date":"2005-12-06"},{"customer-id":"16638567","movie-id":"1037289","rating":3,"date":"2005-12-22"},{"customer-id":"16761155","movie-id":"1037289","rating":4,"date":"2004-04-26"},{"customer-id":"15235650","movie-id":"1037289","rating":3,"date":"2003-01-23"},{"customer-id":"16902777","movie-id":"1037289","rating":3,"date":"2005-06-11"},{"customer-id":"16757459","movie-id":"1037289","rating":4,"date":"2005-11-20"},{"customer-id":"14855333","movie-id":"1037289","rating":2,"date":"2002-02-01"},{"customer-id":"16807189","movie-id":"1037289","rating":3,"date":"2005-06-11"},{"customer-id":"15117642","movie-id":"1037289","rating":4,"date":"2005-06-24"},{"customer-id":"15275068","movie-id":"1037289","rating":5,"date":"2005-09-22"},{"customer-id":"14383795","movie-id":"1037289","rating":3,"date":"2005-11-24"},{"customer-id":"16513521","movie-id":"1037289","rating":5,"date":"2003-02-24"},{"customer-id":"16534655","movie-id":"1037289","rating":2,"date":"2005-10-27"},{"customer-id":"16343695","movie-id":"1037289","rating":2,"date":"2001-04-04"},{"customer-id":"16065581","movie-id":"1037289","rating":4,"date":"2005-07-22"},{"customer-id":"16881896","movie-id":"1037289","rating":1,"date":"2003-04-16"},{"customer-id":"15174105","movie-id":"1037289","rating":3,"date":"2002-01-09"},{"customer-id":"14800502","movie-id":"1037289","rating":1,"date":"2003-03-06"},{"customer-id":"14491585","movie-id":"1037289","rating":4,"date":"2005-03-19"},{"customer-id":"15561898","movie-id":"1037289","rating":5,"date":"2005-03-22"},{"customer-id":"16759453","movie-id":"1037289","rating":3,"date":"2002-03-17"},{"customer-id":"16901870","movie-id":"1037289","rating":2,"date":"2001-02-05"},{"customer-id":"15910145","movie-id":"1037289","rating":2,"date":"2003-06-09"},{"customer-id":"14529969","movie-id":"1037289","rating":5,"date":"2005-10-21"},{"customer-id":"15798776","movie-id":"1037289","rating":5,"date":"2005-11-28"},{"customer-id":"16102102","movie-id":"1037289","rating":5,"date":"2005-05-03"},{"customer-id":"14828140","movie-id":"1037289","rating":2,"date":"2001-06-09"},{"customer-id":"16954634","movie-id":"1037289","rating":4,"date":"2005-05-16"},{"customer-id":"15431943","movie-id":"1037289","rating":3,"date":"2001-08-18"},{"customer-id":"15493835","movie-id":"1037289","rating":1,"date":"2002-01-17"},{"customer-id":"14730627","movie-id":"1037289","rating":4,"date":"2002-01-08"},{"customer-id":"14881187","movie-id":"1037289","rating":4,"date":"2005-12-12"},{"customer-id":"15699669","movie-id":"1037289","rating":5,"date":"2005-09-14"},{"customer-id":"16115407","movie-id":"1037289","rating":4,"date":"2005-10-10"},{"customer-id":"14647260","movie-id":"1037289","rating":4,"date":"2005-11-22"},{"customer-id":"15651433","movie-id":"1037289","rating":2,"date":"2002-07-24"},{"customer-id":"15362774","movie-id":"1037289","rating":3,"date":"2003-06-15"},{"customer-id":"15368504","movie-id":"1037289","rating":3,"date":"2005-04-09"},{"customer-id":"15479520","movie-id":"1037289","rating":4,"date":"2002-06-11"},{"customer-id":"15647722","movie-id":"1037289","rating":3,"date":"2005-04-01"},{"customer-id":"15136849","movie-id":"1037289","rating":1,"date":"2003-01-19"},{"customer-id":"15146131","movie-id":"1037289","rating":1,"date":"2002-10-03"},{"customer-id":"16616597","movie-id":"1037289","rating":4,"date":"2005-06-10"},{"customer-id":"15326739","movie-id":"1037289","rating":2,"date":"2002-08-06"},{"customer-id":"14622487","movie-id":"1037289","rating":5,"date":"2005-08-29"},{"customer-id":"16549717","movie-id":"1037289","rating":3,"date":"2002-02-08"},{"customer-id":"14402705","movie-id":"1037289","rating":1,"date":"2002-06-25"},{"customer-id":"15836038","movie-id":"1037289","rating":3,"date":"2005-07-13"},{"customer-id":"14519896","movie-id":"1037289","rating":1,"date":"2001-12-19"},{"customer-id":"15173188","movie-id":"1037289","rating":5,"date":"2005-12-10"},{"customer-id":"14456232","movie-id":"1037289","rating":1,"date":"2005-04-07"},{"customer-id":"16782850","movie-id":"1037289","rating":3,"date":"2005-05-16"},{"customer-id":"16648765","movie-id":"1037289","rating":1,"date":"2005-12-06"},{"customer-id":"15488879","movie-id":"1037289","rating":2,"date":"2002-08-12"},{"customer-id":"14754783","movie-id":"1037289","rating":4,"date":"2005-09-04"},{"customer-id":"14551411","movie-id":"1037289","rating":5,"date":"2005-07-25"},{"customer-id":"14653179","movie-id":"1037289","rating":1,"date":"2003-02-24"},{"customer-id":"15012710","movie-id":"1037289","rating":2,"date":"2002-06-14"},{"customer-id":"15132230","movie-id":"1037289","rating":4,"date":"2005-06-11"},{"customer-id":"15184096","movie-id":"1037289","rating":3,"date":"2005-05-08"},{"customer-id":"15817948","movie-id":"1037289","rating":3,"date":"2005-06-19"},{"customer-id":"14919927","movie-id":"1037289","rating":4,"date":"2005-10-26"},{"customer-id":"16304983","movie-id":"1037289","rating":3,"date":"2004-07-16"},{"customer-id":"16574345","movie-id":"1037289","rating":2,"date":"2003-08-22"},{"customer-id":"14675236","movie-id":"1037289","rating":1,"date":"2003-01-16"},{"customer-id":"16447281","movie-id":"1037289","rating":3,"date":"2005-06-30"},{"customer-id":"15443840","movie-id":"1037289","rating":5,"date":"2005-11-29"},{"customer-id":"16058493","movie-id":"1037289","rating":2,"date":"2005-12-06"},{"customer-id":"14764395","movie-id":"1037289","rating":3,"date":"2002-09-21"},{"customer-id":"16718979","movie-id":"1037289","rating":1,"date":"2005-10-03"},{"customer-id":"14630489","movie-id":"1037289","rating":1,"date":"2005-06-06"},{"customer-id":"16844009","movie-id":"1037289","rating":1,"date":"2002-11-17"},{"customer-id":"16385528","movie-id":"1037289","rating":5,"date":"2002-04-14"},{"customer-id":"15989633","movie-id":"1037289","rating":2,"date":"2002-01-30"},{"customer-id":"16602007","movie-id":"1037289","rating":2,"date":"2003-06-20"},{"customer-id":"16122315","movie-id":"1037289","rating":2,"date":"2002-09-02"},{"customer-id":"14795594","movie-id":"1037289","rating":5,"date":"2005-10-11"},{"customer-id":"16296845","movie-id":"1037289","rating":1,"date":"2005-10-30"},{"customer-id":"15261166","movie-id":"1037289","rating":3,"date":"2002-10-03"},{"customer-id":"15958480","movie-id":"1037289","rating":5,"date":"2005-08-15"},{"customer-id":"16006497","movie-id":"1037289","rating":4,"date":"2004-04-01"},{"customer-id":"15711133","movie-id":"1037289","rating":1,"date":"2002-08-04"},{"customer-id":"16124290","movie-id":"1037289","rating":5,"date":"2005-11-09"},{"customer-id":"15415596","movie-id":"1037289","rating":3,"date":"2002-12-15"},{"customer-id":"15028169","movie-id":"1037289","rating":4,"date":"2005-08-12"},{"customer-id":"14695343","movie-id":"1037289","rating":4,"date":"2005-04-21"},{"customer-id":"15892436","movie-id":"1037289","rating":5,"date":"2005-12-05"},{"customer-id":"14877835","movie-id":"1037289","rating":5,"date":"2005-07-09"},{"customer-id":"16515731","movie-id":"1037289","rating":2,"date":"2001-08-17"},{"customer-id":"15691399","movie-id":"1037289","rating":2,"date":"2003-07-30"},{"customer-id":"16755829","movie-id":"1037289","rating":3,"date":"2005-11-07"},{"customer-id":"16039853","movie-id":"1037289","rating":3,"date":"2005-12-04"},{"customer-id":"16125846","movie-id":"1037289","rating":3,"date":"2002-06-10"},{"customer-id":"15022762","movie-id":"1037289","rating":2,"date":"2002-09-10"},{"customer-id":"15789999","movie-id":"1037289","rating":2,"date":"2005-09-03"},{"customer-id":"16822130","movie-id":"1037289","rating":3,"date":"2002-09-12"},{"customer-id":"14356217","movie-id":"1037289","rating":3,"date":"2002-09-23"},{"customer-id":"14584125","movie-id":"1037289","rating":4,"date":"2005-04-04"},{"customer-id":"14948559","movie-id":"1037289","rating":3,"date":"2005-11-17"},{"customer-id":"14541760","movie-id":"1037289","rating":3,"date":"2001-11-06"},{"customer-id":"15340181","movie-id":"1037289","rating":3,"date":"2002-01-07"},{"customer-id":"14937517","movie-id":"1037289","rating":2,"date":"2002-07-10"},{"customer-id":"16506582","movie-id":"1037289","rating":1,"date":"2002-09-19"},{"customer-id":"16897066","movie-id":"1037289","rating":5,"date":"2005-10-01"},{"customer-id":"15100477","movie-id":"1037289","rating":2,"date":"2001-02-09"},{"customer-id":"15580086","movie-id":"1037289","rating":2,"date":"2003-06-19"},{"customer-id":"15561960","movie-id":"1037289","rating":3,"date":"2005-05-07"},{"customer-id":"14859734","movie-id":"1037289","rating":2,"date":"2003-06-11"},{"customer-id":"14611248","movie-id":"1037289","rating":4,"date":"2005-05-21"},{"customer-id":"15767689","movie-id":"1037289","rating":3,"date":"2005-10-30"},{"customer-id":"16368744","movie-id":"1037289","rating":2,"date":"2005-12-06"},{"customer-id":"14615524","movie-id":"1037289","rating":3,"date":"2002-06-05"},{"customer-id":"15478791","movie-id":"1037289","rating":3,"date":"2002-10-26"},{"customer-id":"14746496","movie-id":"1037289","rating":2,"date":"2002-06-25"},{"customer-id":"14812339","movie-id":"1037289","rating":2,"date":"2002-10-05"},{"customer-id":"14523206","movie-id":"1037289","rating":3,"date":"2003-07-07"},{"customer-id":"15647190","movie-id":"1037289","rating":1,"date":"2005-05-27"},{"customer-id":"16231385","movie-id":"1037289","rating":5,"date":"2005-06-03"},{"customer-id":"15635325","movie-id":"1037289","rating":3,"date":"2005-10-12"},{"customer-id":"14672908","movie-id":"1037289","rating":2,"date":"2000-12-01"},{"customer-id":"14773178","movie-id":"1037289","rating":3,"date":"2002-01-31"},{"customer-id":"15476752","movie-id":"1037289","rating":4,"date":"2005-08-15"},{"customer-id":"16347520","movie-id":"1037289","rating":3,"date":"2005-03-21"},{"customer-id":"15822095","movie-id":"1037289","rating":1,"date":"2002-04-03"},{"customer-id":"16519659","movie-id":"1037289","rating":3,"date":"2002-10-09"},{"customer-id":"16489923","movie-id":"1037289","rating":4,"date":"2005-11-08"},{"customer-id":"14778483","movie-id":"1037289","rating":4,"date":"2003-03-03"},{"customer-id":"14449735","movie-id":"1037289","rating":4,"date":"2003-06-22"},{"customer-id":"15391885","movie-id":"1037289","rating":4,"date":"2005-09-14"},{"customer-id":"15121468","movie-id":"1037289","rating":5,"date":"2005-12-09"},{"customer-id":"15309376","movie-id":"1037289","rating":3,"date":"2005-12-21"},{"customer-id":"14360633","movie-id":"1037289","rating":3,"date":"2005-07-14"},{"customer-id":"15287901","movie-id":"1037289","rating":3,"date":"2002-04-05"},{"customer-id":"14903595","movie-id":"1037289","rating":3,"date":"2002-02-25"},{"customer-id":"15063732","movie-id":"1037289","rating":5,"date":"2002-10-17"},{"customer-id":"15892615","movie-id":"1037289","rating":3,"date":"2003-06-02"},{"customer-id":"15017805","movie-id":"1037289","rating":4,"date":"2003-04-28"},{"customer-id":"16214158","movie-id":"1037289","rating":3,"date":"2005-05-23"},{"customer-id":"14425060","movie-id":"1037289","rating":3,"date":"2005-10-27"},{"customer-id":"15626106","movie-id":"1037289","rating":3,"date":"2002-02-07"},{"customer-id":"16708652","movie-id":"1037289","rating":3,"date":"2002-01-16"},{"customer-id":"16371946","movie-id":"1037289","rating":2,"date":"2003-08-22"},{"customer-id":"16154350","movie-id":"1037289","rating":4,"date":"2005-10-18"},{"customer-id":"16466296","movie-id":"1037289","rating":5,"date":"2005-11-05"},{"customer-id":"15644332","movie-id":"1037289","rating":2,"date":"2002-06-29"},{"customer-id":"14585121","movie-id":"1037289","rating":1,"date":"2002-08-23"},{"customer-id":"14583043","movie-id":"1037289","rating":5,"date":"2005-11-04"},{"customer-id":"14805738","movie-id":"1037289","rating":5,"date":"2005-11-22"},{"customer-id":"16226383","movie-id":"1037289","rating":5,"date":"2002-04-05"},{"customer-id":"14423653","movie-id":"1037289","rating":4,"date":"2003-01-16"},{"customer-id":"16090594","movie-id":"1037289","rating":3,"date":"2005-10-07"},{"customer-id":"14717197","movie-id":"1037289","rating":5,"date":"2005-07-24"},{"customer-id":"14745051","movie-id":"1037289","rating":4,"date":"2005-07-30"},{"customer-id":"14735253","movie-id":"1037289","rating":1,"date":"2005-05-28"},{"customer-id":"14440959","movie-id":"1037289","rating":2,"date":"2005-06-22"},{"customer-id":"15101996","movie-id":"1037289","rating":3,"date":"2005-11-20"},{"customer-id":"15376998","movie-id":"1037289","rating":1,"date":"2002-05-20"},{"customer-id":"16689188","movie-id":"1037289","rating":2,"date":"2003-06-12"},{"customer-id":"15462159","movie-id":"1037289","rating":4,"date":"2005-03-21"},{"customer-id":"14886947","movie-id":"1037289","rating":3,"date":"2002-10-01"},{"customer-id":"15862174","movie-id":"1037289","rating":4,"date":"2005-04-27"},{"customer-id":"14840126","movie-id":"1037289","rating":2,"date":"2005-05-13"},{"customer-id":"16360247","movie-id":"1037289","rating":3,"date":"2002-09-02"},{"customer-id":"16501556","movie-id":"1037289","rating":1,"date":"2001-08-05"},{"customer-id":"15645871","movie-id":"1037289","rating":4,"date":"2003-04-16"},{"customer-id":"14704450","movie-id":"1037289","rating":1,"date":"2002-05-17"},{"customer-id":"15857814","movie-id":"1037289","rating":2,"date":"2004-03-07"},{"customer-id":"16894555","movie-id":"1037289","rating":1,"date":"2005-08-18"},{"customer-id":"16837602","movie-id":"1037289","rating":3,"date":"2002-07-03"},{"customer-id":"16714512","movie-id":"1037289","rating":4,"date":"2005-08-27"},{"customer-id":"15376376","movie-id":"1037289","rating":3,"date":"2002-02-26"},{"customer-id":"15739672","movie-id":"1037289","rating":5,"date":"2005-11-19"},{"customer-id":"14637545","movie-id":"1037289","rating":2,"date":"2002-02-14"},{"customer-id":"16606150","movie-id":"1037289","rating":1,"date":"2003-06-27"},{"customer-id":"16125799","movie-id":"1037289","rating":1,"date":"2003-06-10"},{"customer-id":"16895784","movie-id":"1037289","rating":3,"date":"2005-07-01"},{"customer-id":"15296636","movie-id":"1037289","rating":2,"date":"2002-01-22"},{"customer-id":"16587044","movie-id":"1037289","rating":3,"date":"2003-02-13"},{"customer-id":"16479629","movie-id":"1037289","rating":4,"date":"2005-07-23"},{"customer-id":"14903961","movie-id":"1037289","rating":1,"date":"2003-03-28"},{"customer-id":"15133766","movie-id":"1037289","rating":4,"date":"2002-07-02"},{"customer-id":"14480964","movie-id":"1037289","rating":4,"date":"2003-02-13"},{"customer-id":"15936341","movie-id":"1037289","rating":3,"date":"2005-10-09"},{"customer-id":"14368783","movie-id":"1037289","rating":3,"date":"2003-03-26"},{"customer-id":"15987627","movie-id":"1037289","rating":1,"date":"2002-03-30"},{"customer-id":"16529353","movie-id":"1037289","rating":1,"date":"2003-02-14"},{"customer-id":"14763909","movie-id":"1037289","rating":4,"date":"2005-08-26"},{"customer-id":"15659422","movie-id":"1037289","rating":4,"date":"2005-05-13"},{"customer-id":"16368310","movie-id":"1037289","rating":1,"date":"2001-06-29"},{"customer-id":"16781813","movie-id":"1037289","rating":2,"date":"2002-01-31"},{"customer-id":"16500509","movie-id":"1037289","rating":4,"date":"2005-10-05"},{"customer-id":"15899148","movie-id":"1037289","rating":3,"date":"2005-10-11"},{"customer-id":"15899850","movie-id":"1037289","rating":4,"date":"2005-05-21"},{"customer-id":"15555300","movie-id":"1037289","rating":4,"date":"2005-09-21"},{"customer-id":"14387210","movie-id":"1037289","rating":2,"date":"2003-01-15"},{"customer-id":"15959008","movie-id":"1037289","rating":1,"date":"2002-05-13"},{"customer-id":"16138411","movie-id":"1037289","rating":4,"date":"2005-05-21"},{"customer-id":"14896929","movie-id":"1037289","rating":1,"date":"2002-03-27"},{"customer-id":"16226633","movie-id":"1037289","rating":1,"date":"2001-02-18"},{"customer-id":"15544511","movie-id":"1037289","rating":3,"date":"2002-08-07"},{"customer-id":"15307677","movie-id":"1037289","rating":4,"date":"2003-03-26"},{"customer-id":"16199875","movie-id":"1037289","rating":1,"date":"2004-04-23"},{"customer-id":"14452559","movie-id":"1037289","rating":2,"date":"2003-05-10"},{"customer-id":"15868049","movie-id":"1037289","rating":4,"date":"2005-06-30"},{"customer-id":"15960736","movie-id":"1037289","rating":3,"date":"2005-11-20"},{"customer-id":"16787369","movie-id":"1037289","rating":4,"date":"2002-12-23"},{"customer-id":"16668532","movie-id":"1037289","rating":1,"date":"2001-12-05"},{"customer-id":"14603012","movie-id":"1037289","rating":3,"date":"2002-12-10"},{"customer-id":"16389485","movie-id":"1037289","rating":3,"date":"2003-07-17"},{"customer-id":"14791282","movie-id":"1037289","rating":4,"date":"2001-06-22"},{"customer-id":"15945404","movie-id":"1037289","rating":1,"date":"2002-03-22"},{"customer-id":"14682536","movie-id":"1037289","rating":4,"date":"2005-05-26"},{"customer-id":"14459659","movie-id":"1037289","rating":4,"date":"2005-12-08"},{"customer-id":"14697844","movie-id":"1037289","rating":5,"date":"2005-12-21"},{"customer-id":"16033383","movie-id":"1037289","rating":1,"date":"2002-07-06"},{"customer-id":"14930466","movie-id":"1037289","rating":2,"date":"2005-11-04"},{"customer-id":"16613363","movie-id":"1037289","rating":1,"date":"2002-06-12"},{"customer-id":"14944368","movie-id":"1037289","rating":5,"date":"2005-03-19"},{"customer-id":"14553922","movie-id":"1037289","rating":5,"date":"2005-04-17"},{"customer-id":"15572574","movie-id":"1037289","rating":4,"date":"2005-05-15"},{"customer-id":"14433004","movie-id":"1037289","rating":4,"date":"2002-09-13"},{"customer-id":"15842220","movie-id":"1037289","rating":3,"date":"2002-11-19"},{"customer-id":"16724018","movie-id":"1037289","rating":4,"date":"2003-03-04"},{"customer-id":"16950589","movie-id":"1037289","rating":3,"date":"2005-06-22"},{"customer-id":"16840530","movie-id":"1037289","rating":1,"date":"2005-12-08"},{"customer-id":"16137380","movie-id":"1037289","rating":3,"date":"2001-08-23"},{"customer-id":"15535602","movie-id":"1037289","rating":3,"date":"2005-07-29"},{"customer-id":"16137993","movie-id":"1037289","rating":4,"date":"2005-11-01"},{"customer-id":"16822019","movie-id":"1037289","rating":3,"date":"2005-11-22"},{"customer-id":"15951586","movie-id":"1037289","rating":5,"date":"2001-05-22"},{"customer-id":"16044450","movie-id":"1037289","rating":5,"date":"2005-04-28"},{"customer-id":"14981573","movie-id":"1037289","rating":3,"date":"2005-10-30"}],"title":"Terror of Mechagodzilla","movieId":"1037289","yearOfRelease":1975}