{"watchedBy":[{"customer-id":"15007629","movie-id":"1027759","rating":2,"date":"2002-04-08"},{"customer-id":"16881661","movie-id":"1027759","rating":2,"date":"2002-01-31"},{"customer-id":"16616408","movie-id":"1027759","rating":1,"date":"2003-01-22"},{"customer-id":"14486513","movie-id":"1027759","rating":1,"date":"2002-06-12"},{"customer-id":"16110940","movie-id":"1027759","rating":3,"date":"2002-12-15"},{"customer-id":"16156765","movie-id":"1027759","rating":2,"date":"2005-07-26"},{"customer-id":"14972920","movie-id":"1027759","rating":2,"date":"2002-12-19"},{"customer-id":"14919382","movie-id":"1027759","rating":2,"date":"2002-07-21"},{"customer-id":"14513788","movie-id":"1027759","rating":2,"date":"2005-01-22"},{"customer-id":"16222370","movie-id":"1027759","rating":2,"date":"2002-12-21"},{"customer-id":"15507640","movie-id":"1027759","rating":1,"date":"2002-02-04"},{"customer-id":"16574419","movie-id":"1027759","rating":2,"date":"2002-07-02"},{"customer-id":"14962650","movie-id":"1027759","rating":1,"date":"2003-11-04"},{"customer-id":"16373412","movie-id":"1027759","rating":2,"date":"2003-03-25"},{"customer-id":"16614001","movie-id":"1027759","rating":1,"date":"2002-06-30"},{"customer-id":"15906857","movie-id":"1027759","rating":2,"date":"2005-01-13"},{"customer-id":"16491705","movie-id":"1027759","rating":3,"date":"2002-09-16"},{"customer-id":"15132213","movie-id":"1027759","rating":1,"date":"2003-03-10"},{"customer-id":"16921042","movie-id":"1027759","rating":1,"date":"2002-08-06"},{"customer-id":"14399911","movie-id":"1027759","rating":3,"date":"2004-07-28"},{"customer-id":"15397918","movie-id":"1027759","rating":2,"date":"2002-02-21"},{"customer-id":"15836069","movie-id":"1027759","rating":1,"date":"2002-07-09"},{"customer-id":"16424984","movie-id":"1027759","rating":2,"date":"2002-09-11"},{"customer-id":"14974495","movie-id":"1027759","rating":1,"date":"2002-05-31"},{"customer-id":"15879960","movie-id":"1027759","rating":2,"date":"2003-09-16"},{"customer-id":"15323034","movie-id":"1027759","rating":1,"date":"2002-09-27"},{"customer-id":"16078026","movie-id":"1027759","rating":3,"date":"2003-03-04"},{"customer-id":"14551931","movie-id":"1027759","rating":3,"date":"2003-05-31"},{"customer-id":"15816655","movie-id":"1027759","rating":3,"date":"2004-05-19"},{"customer-id":"16838222","movie-id":"1027759","rating":1,"date":"2002-05-01"},{"customer-id":"15952432","movie-id":"1027759","rating":1,"date":"2002-04-10"},{"customer-id":"15550481","movie-id":"1027759","rating":2,"date":"2003-03-12"},{"customer-id":"16452416","movie-id":"1027759","rating":1,"date":"2003-05-12"},{"customer-id":"16054137","movie-id":"1027759","rating":3,"date":"2002-10-22"},{"customer-id":"15091386","movie-id":"1027759","rating":1,"date":"2002-11-08"},{"customer-id":"16616874","movie-id":"1027759","rating":2,"date":"2003-08-20"},{"customer-id":"16019994","movie-id":"1027759","rating":3,"date":"2004-01-27"},{"customer-id":"16913438","movie-id":"1027759","rating":2,"date":"2003-08-08"},{"customer-id":"16363762","movie-id":"1027759","rating":3,"date":"2002-12-02"},{"customer-id":"15274052","movie-id":"1027759","rating":2,"date":"2002-11-13"},{"customer-id":"16459527","movie-id":"1027759","rating":2,"date":"2002-02-24"},{"customer-id":"14809399","movie-id":"1027759","rating":2,"date":"2002-12-04"},{"customer-id":"16730584","movie-id":"1027759","rating":2,"date":"2004-03-29"},{"customer-id":"14916578","movie-id":"1027759","rating":4,"date":"2003-03-31"},{"customer-id":"16892808","movie-id":"1027759","rating":2,"date":"2002-10-12"},{"customer-id":"14575780","movie-id":"1027759","rating":1,"date":"2003-04-17"},{"customer-id":"16224355","movie-id":"1027759","rating":1,"date":"2002-05-10"},{"customer-id":"14842876","movie-id":"1027759","rating":1,"date":"2005-09-26"},{"customer-id":"15098980","movie-id":"1027759","rating":3,"date":"2004-01-03"},{"customer-id":"15572618","movie-id":"1027759","rating":2,"date":"2003-08-07"},{"customer-id":"15622419","movie-id":"1027759","rating":2,"date":"2003-06-23"},{"customer-id":"16530177","movie-id":"1027759","rating":3,"date":"2004-03-05"},{"customer-id":"14972806","movie-id":"1027759","rating":1,"date":"2003-09-09"},{"customer-id":"16716411","movie-id":"1027759","rating":3,"date":"2004-07-13"},{"customer-id":"16177835","movie-id":"1027759","rating":2,"date":"2005-07-21"},{"customer-id":"16404507","movie-id":"1027759","rating":2,"date":"2002-09-26"},{"customer-id":"16431202","movie-id":"1027759","rating":3,"date":"2002-11-13"},{"customer-id":"16634215","movie-id":"1027759","rating":2,"date":"2003-10-31"},{"customer-id":"15858983","movie-id":"1027759","rating":2,"date":"2002-08-18"},{"customer-id":"16011845","movie-id":"1027759","rating":2,"date":"2005-10-12"},{"customer-id":"16298534","movie-id":"1027759","rating":3,"date":"2003-11-03"},{"customer-id":"15823039","movie-id":"1027759","rating":2,"date":"2002-03-20"},{"customer-id":"15786554","movie-id":"1027759","rating":2,"date":"2002-11-25"},{"customer-id":"15953047","movie-id":"1027759","rating":1,"date":"2002-07-10"},{"customer-id":"16465987","movie-id":"1027759","rating":2,"date":"2003-03-08"},{"customer-id":"15452719","movie-id":"1027759","rating":2,"date":"2002-12-21"},{"customer-id":"16351637","movie-id":"1027759","rating":3,"date":"2002-10-17"},{"customer-id":"14638765","movie-id":"1027759","rating":3,"date":"2003-02-26"},{"customer-id":"16534340","movie-id":"1027759","rating":1,"date":"2003-08-22"},{"customer-id":"15238934","movie-id":"1027759","rating":3,"date":"2002-06-18"},{"customer-id":"15159247","movie-id":"1027759","rating":1,"date":"2004-06-03"},{"customer-id":"16919620","movie-id":"1027759","rating":3,"date":"2002-10-31"},{"customer-id":"15986476","movie-id":"1027759","rating":2,"date":"2003-06-24"},{"customer-id":"14973683","movie-id":"1027759","rating":3,"date":"2004-05-26"},{"customer-id":"14898788","movie-id":"1027759","rating":1,"date":"2003-04-04"},{"customer-id":"16953729","movie-id":"1027759","rating":2,"date":"2002-05-02"},{"customer-id":"16014048","movie-id":"1027759","rating":1,"date":"2002-04-17"},{"customer-id":"16854809","movie-id":"1027759","rating":2,"date":"2003-02-26"},{"customer-id":"14879368","movie-id":"1027759","rating":2,"date":"2002-07-14"},{"customer-id":"16437434","movie-id":"1027759","rating":1,"date":"2004-01-19"},{"customer-id":"16459836","movie-id":"1027759","rating":1,"date":"2002-03-28"},{"customer-id":"15493835","movie-id":"1027759","rating":1,"date":"2002-01-27"},{"customer-id":"15146229","movie-id":"1027759","rating":2,"date":"2003-05-13"},{"customer-id":"14871813","movie-id":"1027759","rating":5,"date":"2003-12-18"},{"customer-id":"15136849","movie-id":"1027759","rating":1,"date":"2003-01-19"},{"customer-id":"15146131","movie-id":"1027759","rating":1,"date":"2002-11-21"},{"customer-id":"16643429","movie-id":"1027759","rating":2,"date":"2005-09-02"},{"customer-id":"15270984","movie-id":"1027759","rating":1,"date":"2003-04-13"},{"customer-id":"16989659","movie-id":"1027759","rating":3,"date":"2005-11-29"},{"customer-id":"14653179","movie-id":"1027759","rating":3,"date":"2003-05-16"},{"customer-id":"15582066","movie-id":"1027759","rating":4,"date":"2002-07-27"},{"customer-id":"16385913","movie-id":"1027759","rating":2,"date":"2003-11-21"},{"customer-id":"14725050","movie-id":"1027759","rating":3,"date":"2003-07-07"},{"customer-id":"16073286","movie-id":"1027759","rating":1,"date":"2005-04-19"},{"customer-id":"14792194","movie-id":"1027759","rating":2,"date":"2002-08-24"},{"customer-id":"15886190","movie-id":"1027759","rating":1,"date":"2004-03-10"},{"customer-id":"16987905","movie-id":"1027759","rating":2,"date":"2003-06-17"},{"customer-id":"16453437","movie-id":"1027759","rating":2,"date":"2003-08-28"},{"customer-id":"16010028","movie-id":"1027759","rating":2,"date":"2003-04-24"},{"customer-id":"15120660","movie-id":"1027759","rating":1,"date":"2003-02-26"},{"customer-id":"15783051","movie-id":"1027759","rating":2,"date":"2002-10-12"},{"customer-id":"16045076","movie-id":"1027759","rating":2,"date":"2002-03-05"},{"customer-id":"16189240","movie-id":"1027759","rating":1,"date":"2003-04-09"},{"customer-id":"15990216","movie-id":"1027759","rating":1,"date":"2002-08-28"},{"customer-id":"16766704","movie-id":"1027759","rating":2,"date":"2003-01-20"},{"customer-id":"15203876","movie-id":"1027759","rating":1,"date":"2003-08-14"},{"customer-id":"15403787","movie-id":"1027759","rating":2,"date":"2003-03-26"},{"customer-id":"16069889","movie-id":"1027759","rating":5,"date":"2003-08-26"},{"customer-id":"15957486","movie-id":"1027759","rating":2,"date":"2002-01-26"},{"customer-id":"15020294","movie-id":"1027759","rating":1,"date":"2002-05-08"},{"customer-id":"16652809","movie-id":"1027759","rating":2,"date":"2003-03-10"},{"customer-id":"14970288","movie-id":"1027759","rating":3,"date":"2003-10-27"},{"customer-id":"16466296","movie-id":"1027759","rating":2,"date":"2005-12-20"},{"customer-id":"16283223","movie-id":"1027759","rating":2,"date":"2003-01-24"},{"customer-id":"14735253","movie-id":"1027759","rating":2,"date":"2003-08-21"},{"customer-id":"14788637","movie-id":"1027759","rating":3,"date":"2002-02-14"},{"customer-id":"15376998","movie-id":"1027759","rating":1,"date":"2002-06-29"},{"customer-id":"15106188","movie-id":"1027759","rating":4,"date":"2002-08-01"},{"customer-id":"15080551","movie-id":"1027759","rating":2,"date":"2003-07-18"},{"customer-id":"16913135","movie-id":"1027759","rating":3,"date":"2003-05-06"},{"customer-id":"16209930","movie-id":"1027759","rating":1,"date":"2003-04-24"},{"customer-id":"16797750","movie-id":"1027759","rating":2,"date":"2002-03-17"},{"customer-id":"15481034","movie-id":"1027759","rating":2,"date":"2002-05-31"},{"customer-id":"15409030","movie-id":"1027759","rating":1,"date":"2003-12-14"},{"customer-id":"15606830","movie-id":"1027759","rating":2,"date":"2002-04-12"},{"customer-id":"15809270","movie-id":"1027759","rating":1,"date":"2002-02-07"},{"customer-id":"14833436","movie-id":"1027759","rating":3,"date":"2003-05-15"},{"customer-id":"16083465","movie-id":"1027759","rating":1,"date":"2004-10-27"},{"customer-id":"15987627","movie-id":"1027759","rating":1,"date":"2002-05-11"},{"customer-id":"15510300","movie-id":"1027759","rating":3,"date":"2002-05-25"},{"customer-id":"15128856","movie-id":"1027759","rating":3,"date":"2003-02-12"},{"customer-id":"16726753","movie-id":"1027759","rating":3,"date":"2002-07-17"},{"customer-id":"16978689","movie-id":"1027759","rating":1,"date":"2002-04-08"},{"customer-id":"16697537","movie-id":"1027759","rating":2,"date":"2002-07-22"},{"customer-id":"16183141","movie-id":"1027759","rating":3,"date":"2002-08-07"},{"customer-id":"14498179","movie-id":"1027759","rating":2,"date":"2002-02-10"},{"customer-id":"16576681","movie-id":"1027759","rating":1,"date":"2002-10-13"},{"customer-id":"16996688","movie-id":"1027759","rating":2,"date":"2002-12-28"}],"title":"A Girl","movieId":"1027759","yearOfRelease":2001}