{"watchedBy":[{"customer-id":"16544703","movie-id":"1025156","rating":2,"date":"2003-04-21"},{"customer-id":"14424031","movie-id":"1025156","rating":4,"date":"2003-08-08"},{"customer-id":"15534327","movie-id":"1025156","rating":3,"date":"2005-08-25"},{"customer-id":"15104953","movie-id":"1025156","rating":3,"date":"2005-12-06"},{"customer-id":"14793663","movie-id":"1025156","rating":2,"date":"2004-08-15"},{"customer-id":"14761472","movie-id":"1025156","rating":4,"date":"2003-11-04"},{"customer-id":"15165380","movie-id":"1025156","rating":2,"date":"2001-01-14"},{"customer-id":"14503177","movie-id":"1025156","rating":1,"date":"2003-03-30"},{"customer-id":"14443832","movie-id":"1025156","rating":3,"date":"2005-10-08"},{"customer-id":"16751534","movie-id":"1025156","rating":4,"date":"2004-12-30"},{"customer-id":"16305288","movie-id":"1025156","rating":4,"date":"2004-05-01"},{"customer-id":"14552274","movie-id":"1025156","rating":4,"date":"2000-09-21"},{"customer-id":"15810794","movie-id":"1025156","rating":2,"date":"2003-01-16"},{"customer-id":"14456706","movie-id":"1025156","rating":3,"date":"2000-01-07"},{"customer-id":"15480416","movie-id":"1025156","rating":3,"date":"2002-08-24"},{"customer-id":"14479929","movie-id":"1025156","rating":1,"date":"2003-09-09"},{"customer-id":"15729878","movie-id":"1025156","rating":2,"date":"2005-02-15"},{"customer-id":"15322978","movie-id":"1025156","rating":4,"date":"2004-03-29"},{"customer-id":"16787328","movie-id":"1025156","rating":1,"date":"2003-03-23"},{"customer-id":"14793895","movie-id":"1025156","rating":3,"date":"2004-09-02"},{"customer-id":"16128655","movie-id":"1025156","rating":5,"date":"2005-04-04"},{"customer-id":"16350477","movie-id":"1025156","rating":1,"date":"2003-10-03"},{"customer-id":"14571317","movie-id":"1025156","rating":2,"date":"2005-08-31"},{"customer-id":"16905470","movie-id":"1025156","rating":1,"date":"2005-11-06"},{"customer-id":"15789175","movie-id":"1025156","rating":4,"date":"2002-09-11"},{"customer-id":"14667129","movie-id":"1025156","rating":3,"date":"2003-07-18"},{"customer-id":"16208791","movie-id":"1025156","rating":3,"date":"2002-09-04"},{"customer-id":"16388694","movie-id":"1025156","rating":1,"date":"2004-11-23"},{"customer-id":"15976277","movie-id":"1025156","rating":4,"date":"2003-04-09"},{"customer-id":"15812745","movie-id":"1025156","rating":2,"date":"2002-08-06"},{"customer-id":"15142294","movie-id":"1025156","rating":4,"date":"2005-11-06"},{"customer-id":"16448104","movie-id":"1025156","rating":3,"date":"2004-05-18"},{"customer-id":"16224355","movie-id":"1025156","rating":1,"date":"2002-05-30"},{"customer-id":"16845680","movie-id":"1025156","rating":3,"date":"2003-04-01"},{"customer-id":"15854442","movie-id":"1025156","rating":1,"date":"2003-08-18"},{"customer-id":"16710253","movie-id":"1025156","rating":3,"date":"2004-09-10"},{"customer-id":"14382008","movie-id":"1025156","rating":3,"date":"2005-07-21"},{"customer-id":"16154585","movie-id":"1025156","rating":2,"date":"2003-11-27"},{"customer-id":"15654139","movie-id":"1025156","rating":3,"date":"2002-11-13"},{"customer-id":"15367326","movie-id":"1025156","rating":3,"date":"2004-05-14"},{"customer-id":"16935502","movie-id":"1025156","rating":3,"date":"2005-01-04"},{"customer-id":"15376861","movie-id":"1025156","rating":3,"date":"2003-07-28"},{"customer-id":"16805616","movie-id":"1025156","rating":2,"date":"2004-09-13"},{"customer-id":"15547618","movie-id":"1025156","rating":2,"date":"2005-04-10"},{"customer-id":"15889576","movie-id":"1025156","rating":1,"date":"2005-03-28"},{"customer-id":"16011845","movie-id":"1025156","rating":3,"date":"2005-10-14"},{"customer-id":"15029453","movie-id":"1025156","rating":3,"date":"2005-02-28"},{"customer-id":"16903449","movie-id":"1025156","rating":4,"date":"2002-01-22"},{"customer-id":"15384781","movie-id":"1025156","rating":3,"date":"2004-03-31"},{"customer-id":"15581596","movie-id":"1025156","rating":2,"date":"2003-06-27"},{"customer-id":"16768518","movie-id":"1025156","rating":2,"date":"2003-12-22"},{"customer-id":"16065193","movie-id":"1025156","rating":5,"date":"2005-07-20"},{"customer-id":"16325151","movie-id":"1025156","rating":1,"date":"2002-05-10"},{"customer-id":"16954990","movie-id":"1025156","rating":2,"date":"2003-01-23"},{"customer-id":"15615020","movie-id":"1025156","rating":5,"date":"2004-03-12"},{"customer-id":"16056203","movie-id":"1025156","rating":2,"date":"2003-04-11"},{"customer-id":"15090911","movie-id":"1025156","rating":3,"date":"2005-06-01"},{"customer-id":"14980889","movie-id":"1025156","rating":3,"date":"2004-10-05"},{"customer-id":"15403310","movie-id":"1025156","rating":3,"date":"2004-05-15"},{"customer-id":"14653179","movie-id":"1025156","rating":3,"date":"2003-05-17"},{"customer-id":"16232395","movie-id":"1025156","rating":3,"date":"2004-09-18"},{"customer-id":"16554877","movie-id":"1025156","rating":5,"date":"2003-01-09"},{"customer-id":"15932727","movie-id":"1025156","rating":3,"date":"2005-09-09"},{"customer-id":"14469583","movie-id":"1025156","rating":3,"date":"2005-03-02"},{"customer-id":"16504334","movie-id":"1025156","rating":4,"date":"2005-01-13"},{"customer-id":"16955477","movie-id":"1025156","rating":3,"date":"2003-03-31"},{"customer-id":"16117642","movie-id":"1025156","rating":1,"date":"2005-05-09"},{"customer-id":"15900964","movie-id":"1025156","rating":2,"date":"2005-07-24"},{"customer-id":"15835867","movie-id":"1025156","rating":4,"date":"2005-07-19"},{"customer-id":"16819852","movie-id":"1025156","rating":2,"date":"2003-03-18"},{"customer-id":"15527817","movie-id":"1025156","rating":2,"date":"2002-01-09"},{"customer-id":"14989970","movie-id":"1025156","rating":5,"date":"2005-02-13"},{"customer-id":"16465574","movie-id":"1025156","rating":4,"date":"2004-01-12"},{"customer-id":"16085725","movie-id":"1025156","rating":1,"date":"2004-10-11"},{"customer-id":"16385362","movie-id":"1025156","rating":3,"date":"2005-06-15"},{"customer-id":"16466296","movie-id":"1025156","rating":3,"date":"2005-12-20"},{"customer-id":"15644332","movie-id":"1025156","rating":2,"date":"2002-06-26"},{"customer-id":"14735253","movie-id":"1025156","rating":2,"date":"2003-09-11"},{"customer-id":"16063715","movie-id":"1025156","rating":2,"date":"2005-06-13"},{"customer-id":"15462159","movie-id":"1025156","rating":1,"date":"2005-10-01"},{"customer-id":"14819442","movie-id":"1025156","rating":3,"date":"2004-11-13"},{"customer-id":"16507852","movie-id":"1025156","rating":2,"date":"2003-03-20"},{"customer-id":"16011723","movie-id":"1025156","rating":4,"date":"2004-07-08"},{"customer-id":"15810111","movie-id":"1025156","rating":3,"date":"2004-04-26"},{"customer-id":"16047785","movie-id":"1025156","rating":2,"date":"2005-07-20"},{"customer-id":"15987627","movie-id":"1025156","rating":1,"date":"2002-04-10"},{"customer-id":"15486629","movie-id":"1025156","rating":4,"date":"2005-05-20"},{"customer-id":"14364784","movie-id":"1025156","rating":4,"date":"2005-01-22"},{"customer-id":"15981564","movie-id":"1025156","rating":3,"date":"2003-11-12"},{"customer-id":"16226633","movie-id":"1025156","rating":1,"date":"2001-02-18"},{"customer-id":"15065989","movie-id":"1025156","rating":1,"date":"2005-09-09"},{"customer-id":"16067031","movie-id":"1025156","rating":2,"date":"2005-11-21"},{"customer-id":"15826065","movie-id":"1025156","rating":4,"date":"2003-12-03"},{"customer-id":"15044808","movie-id":"1025156","rating":1,"date":"2004-06-03"},{"customer-id":"15993676","movie-id":"1025156","rating":4,"date":"2004-02-18"},{"customer-id":"14476285","movie-id":"1025156","rating":3,"date":"2003-04-07"}],"title":"Travel the World by Train: Africa","movieId":"1025156","yearOfRelease":1999}